mancala/__init__.py
mancala/agents/__init__.py
mancala/agents/base.py
mancala/agents/exact.py
mancala/agents/human.py
mancala/agents/max.py
mancala/agents/minimax.py
mancala/agents/negascout.py
mancala/agents/random.py
mancala/agents/value_iteration.py
mancala/arena.py
mancala/cli.py
mancala/game.py
mancala/mancala.py
mancala/play.py
mancala/rule.py
mancala/state/__init__.py
mancala/state/base.py
mancala/train.py
mancala-0.3.0.dist-info/entry_points.txt
mancala-0.3.0.dist-info/WHEEL
mancala-0.3.0.dist-info/METADATA
mancala-0.3.0.dist-info/RECORD
