Metadata-Version: 2.1
Name: mancala
Version: 0.3.0
Summary: Mancala written in Python, playable in CLI (GUI coming soon)!
Home-page: https://github.com/qqhann/Mancala
License: MIT
Keywords: mancala,game,gym,reinforcement learning
Author: Qiushi Pan
Author-email: qiu.gits@gmail.com
Requires-Python: >=3.8,<4.0
Classifier: License :: OSI Approved :: MIT License
Classifier: Programming Language :: Python :: 3
Classifier: Programming Language :: Python :: 3.8
Classifier: Programming Language :: Python :: 3.9
Requires-Dist: gym (>=0.18.0,<0.19.0)
Requires-Dist: numpy (>=1.20.1,<2.0.0)
Requires-Dist: pandas (>=1.2.4,<2.0.0)
Requires-Dist: tqdm (>=4.60.0,<5.0.0)
Project-URL: Repository, https://github.com/qqhann/Mancala
